{
  "generator-jhipster": {
    "jhipsterVersion": "4.0.8",
    "baseName": "blog",
    "packageName": "org.jhipster",
    "packageFolder": "org/jhipster",
    "serverPort": "8080",
    "authenticationType": "jwt",
    "hibernateCache": "ehcache",
    "clusteredHttpSession": false,
    "websocket": false,
    "databaseType": "sql",
    "devDatabaseType": "h2Disk",
    "prodDatabaseType": "postgresql",
    "searchEngine": false,
    "messageBroker": false,
    "serviceDiscoveryType": false,
    "buildTool": "maven",
    "enableSocialSignIn": false,
    "jwtSecretKey": "a895eda190e4ddf6eba453aa725bb4da8a565dfc",
    "clientFramework": "angular2",
    "useSass": true,
    "clientPackageManager": "yarn",
    "applicationType": "monolith",
    "testFrameworks": [
      "gatling",
      "protractor"
    ],
    "jhiPrefix": "jhi",
    "enableTranslation": true,
    "nativeLanguage": "en",
    "languages": [
      "en",
      "es"
    ]
  }
}